CHANGES
README
setup.py
cmsutils/__init__.py
cmsutils/adminfilters.py
cmsutils/cache.py
cmsutils/compat.py
cmsutils/db_utils.py
cmsutils/decorators.py
cmsutils/docfilters.py
cmsutils/exceptions.py
cmsutils/i18n.py
cmsutils/log.py
cmsutils/longtask.py
cmsutils/managers.py
cmsutils/map_utils.py
cmsutils/middleware.py
cmsutils/models.py
cmsutils/resourcemanager.py
cmsutils/search.py
cmsutils/signals.py
cmsutils/spidertests.py
cmsutils/tag_utils.py
cmsutils/tests.py
cmsutils/upload_handlers.py
cmsutils/utils.py
cmsutils/uuid25.py
cmsutils.egg-info/PKG-INFO
cmsutils.egg-info/SOURCES.txt
cmsutils.egg-info/dependency_links.txt
cmsutils.egg-info/top_level.txt
cmsutils/auth/__init__.py
cmsutils/auth/backends.py
cmsutils/db/__init__.py
cmsutils/db/fields.py
cmsutils/docs/CREDITS.TXT
cmsutils/docs/LICENSE.GPL
cmsutils/docs/LICENSE.txt
cmsutils/forms/__init__.py
cmsutils/forms/fields.py
cmsutils/forms/forms.py
cmsutils/forms/gridform.py
cmsutils/forms/widgets.py
cmsutils/forms/wtform.py
cmsutils/locale/es/LC_MESSAGES/django.mo
cmsutils/locale/es/LC_MESSAGES/django.po
cmsutils/management/__init__.py
cmsutils/management/commands/__init__.py
cmsutils/management/commands/backupdb.py
cmsutils/management/commands/freshdb.py
cmsutils/management/commands/indexdocs.py
cmsutils/management/commands/install_media.py
cmsutils/management/commands/load_production_db.py
cmsutils/management/commands/pack_fixtures.py
cmsutils/management/commands/rebuild_db.py
cmsutils/management/commands/save_fixtures.py
cmsutils/media/css/jquery.autocomplete.css
cmsutils/media/css/longtask.css
cmsutils/media/css/widgets/colorpicker.css
cmsutils/media/img/icon_view.gif
cmsutils/media/img/widgets/colorpicker/blank.gif
cmsutils/media/img/widgets/colorpicker/colorpicker_background.png
cmsutils/media/img/widgets/colorpicker/colorpicker_hex.png
cmsutils/media/img/widgets/colorpicker/colorpicker_hsb_b.png
cmsutils/media/img/widgets/colorpicker/colorpicker_hsb_h.png
cmsutils/media/img/widgets/colorpicker/colorpicker_hsb_s.png
cmsutils/media/img/widgets/colorpicker/colorpicker_indic.gif
