Metadata-Version: 1.0
Name: cmsutils
Version: 0.6.6
Summary: Cmsutils for Django is a bundle of models and templates for Django projects in need of some Content Management System features.
Home-page: http://tracpub.yaco.es/cmsutils
Author: Yaco Sistemas S.L.
Author-email: msaelices@yaco.es
License: LGPL 3
Keywords: django cms utils tools
Platform: UNKNOWN
Classifier: Development Status :: 4 - Beta
Classifier: Framework :: Django
Classifier: License :: OSI Approved :: GNU Library or Lesser General Public License (LGPL)
